devpi_plumber/__init__.py
devpi_plumber/client.py
devpi_plumber/server.py
devpi_plumber-0.7.0.dist-info/COPYING
devpi_plumber-0.7.0.dist-info/METADATA
devpi_plumber-0.7.0.dist-info/WHEEL
devpi_plumber-0.7.0.dist-info/top_level.txt
devpi_plumber-0.7.0.dist-info/RECORD
