Metadata-Version: 2.1
Name: devpi-plumber
Version: 0.7.0
Summary: Mario, the devpi-plumber, helps to automate and test large devpi installations.
Home-page: https://github.com/blue-yonder/devpi-plumber
Author: Stephan Erb
Author-email: stephan.erb@blue-yonder.com
License: new BSD
Classifier: Development Status :: 4 - Beta
Classifier: Environment :: Console
Classifier: Intended Audience :: Developers
Classifier: Intended Audience :: System Administrators
Classifier: License :: OSI Approved :: BSD License
Classifier: Topic :: System :: Archiving :: Packaging
Classifier: Programming Language :: Python :: 3
Classifier: Programming Language :: Python :: 3.8
Classifier: Programming Language :: Python :: 3.9
Classifier: Programming Language :: Python :: 3.10
Classifier: Programming Language :: Python :: 3.11
Classifier: Programming Language :: Python :: 3.12
License-File: COPYING
Requires-Dist: devpi-client
Requires-Dist: requests
Requires-Dist: twitter.common.contextutil
Provides-Extra: test
Requires-Dist: devpi-server >=5.2.0 ; extra == 'test'
